dell_projector/__init__.py
dell_projector/main.py
dell_projector-0.0.2.dist-info/LICENSE
dell_projector-0.0.2.dist-info/METADATA
dell_projector-0.0.2.dist-info/WHEEL
dell_projector-0.0.2.dist-info/top_level.txt
dell_projector-0.0.2.dist-info/RECORD
