Metadata-Version: 2.1
Name: dell-projector
Version: 0.0.2
Summary: A utility to control dell projectors and query their status
Home-page: https://github.com/abhiseshan/dell-projector
Author: Abhinav Rajaseshan
Author-email: abhinavrajaseshan@gmail.com
License: UNKNOWN
Platform: UNKNOWN
Classifier: Programming Language :: Python :: 3
Classifier: License :: OSI Approved :: MIT License
Classifier: Operating System :: OS Independent
Requires-Python: >=3.6
